{
  "htmlContent": "\u003cp\u003eUnless US Player immediately discards a \u0026lsquo;3\u0026rsquo; or more value Operations card, eliminate all US Influence in West Germany.\u003c/p\u003e\n",
  "name": "Blockade*",
  "number": 10,
  "ops": 1,
  "period": "E",
  "permalink": "/cards/010/printed/",
  "plainContent": "Unless US Player immediately discards a \u0026lsquo;3\u0026rsquo; or more value Operations card, eliminate all US Influence in West Germany.\n",
  "side": "USSR",
  "types": [
    "unique"
  ],
  "version": "printed"
}
