{
  "htmlContent": "\u003cp\u003eGain 3 military operations.\u003c/p\u003e\n\u003cp\u003eChoose a country with stability less than 3. Roll a die and subtract 1 for each enemy-controlled country adjacent to the chosen country. If the result is 4 or greater, gain 1 VP, remove all enemy influence from the chosen country, and place friendly influence there equal to the amount removed.\u003c/p\u003e\n",
  "name": "Brush War",
  "number": 36,
  "ops": 3,
  "period": "M",
  "permalink": "twilight-oracle.github.io/cards/036/oracle/",
  "plainContent": "Gain 3 military operations.\nChoose a country with stability less than 3. Roll a die and subtract 1 for each enemy-controlled country adjacent to the chosen country. If the result is 4 or greater, gain 1 VP, remove all enemy influence from the chosen country, and place friendly influence there equal to the amount removed.\n",
  "side": "none",
  "types": [
    "war"
  ],
  "version": "oracle"
}
