{
  "htmlContent": "\u003cp\u003eAll of the player\u0026rsquo;s Coup attempts in Central and South America are +1 for the remainder of the turn, while all opponent\u0026rsquo;s Coup attempts are -1 for the remainder of the turn.\u003c/p\u003e\n",
  "name": "Latin American Death Squads",
  "number": 69,
  "ops": 2,
  "period": "M",
  "permalink": "twilight-oracle.github.io/cards/069/printed/",
  "plainContent": "All of the player\u0026rsquo;s Coup attempts in Central and South America are +1 for the remainder of the turn, while all opponent\u0026rsquo;s Coup attempts are -1 for the remainder of the turn.\n",
  "side": "none",
  "types": [],
  "version": "printed"
}
